tests/__init__.py
bassa-0.0.1.dist-info/RECORD
bassa-0.0.1.dist-info/pbr.json
bassa-0.0.1.dist-info/entry_points.txt
bassa-0.0.1.dist-info/WHEEL
bassa-0.0.1.dist-info/top_level.txt
bassa-0.0.1.dist-info/METADATA
bassa-0.0.1.dist-info/metadata.json
bassa-0.0.1.dist-info/DESCRIPTION.rst
